pdfimpose/__init__.py
pdfimpose/__main__.py
pdfimpose/pdf.py
pdfimpose/apply/__init__.py
pdfimpose/apply/__main__.py
pdfimpose/schema/__init__.py
pdfimpose/schema/cards/__init__.py
pdfimpose/schema/cards/__main__.py
pdfimpose/schema/copycutfold/__init__.py
pdfimpose/schema/copycutfold/__main__.py
pdfimpose/schema/cutstackfold/__init__.py
pdfimpose/schema/cutstackfold/__main__.py
pdfimpose/schema/hardcover/__init__.py
pdfimpose/schema/hardcover/__main__.py
pdfimpose/schema/onepagezine/__init__.py
pdfimpose/schema/onepagezine/__main__.py
pdfimpose/schema/perfect/__init__.py
pdfimpose/schema/perfect/__main__.py
pdfimpose/schema/saddle/__init__.py
pdfimpose/schema/saddle/__main__.py
pdfimpose/schema/wire/__init__.py
pdfimpose/schema/wire/__main__.py
pdfimpose-2.8.0.dist-info/licenses/AUTHORS
pdfimpose-2.8.0.dist-info/licenses/LICENSE
pdfimpose-2.8.0.dist-info/METADATA
pdfimpose-2.8.0.dist-info/WHEEL
pdfimpose-2.8.0.dist-info/entry_points.txt
pdfimpose-2.8.0.dist-info/top_level.txt
pdfimpose-2.8.0.dist-info/zip-safe
pdfimpose-2.8.0.dist-info/RECORD
