Metadata-Version: 2.4
Name: pdfimpose
Version: 2.8.0
Summary: Perform imposition of a PDF file.
Home-page: http://framagit.org/spalax/pdfimpose
Author: Louis Paternault
Author-email: spalax@gresille.org
License: AGPLv3 or any later version
Project-URL: Documentation, http://pdfimpose.readthedocs.io
Project-URL: Source, https://framagit.org/spalax/pdfimpose
Project-URL: Tracker, https://framagit.org/spalax/pdfimpose/issues
Keywords: pdf imposition print
Classifier: Development Status :: 5 - Production/Stable
Classifier: Environment :: Console
Classifier: License :: OSI Approved :: GNU Affero General Public License v3 or later (AGPLv3+)
Classifier: Operating System :: OS Independent
Classifier: Programming Language :: Python :: 3
Classifier: Programming Language :: Python :: 3.10
Classifier: Programming Language :: Python :: 3.11
Classifier: Programming Language :: Python :: 3.12
Classifier: Programming Language :: Python :: 3.13
Classifier: Programming Language :: Python :: 3.14
Classifier: Topic :: Printing
Requires-Python: <4,>=3.10
License-File: LICENSE
License-File: AUTHORS
Requires-Dist: argdispatch
Requires-Dist: papersize
Requires-Dist: pymupdf>=1.24.3
Requires-Dist: pyxdg
Dynamic: license-file
